<annotation>
	<folder>images</folder>
	<filename>00108.jpg</filename>
	<path>/home/dpidave/training_resources/tf-object-detection-tutorial/Tensorflow/workspace/training_demo/images/00108.jpg</path>
	<source>
		<database>Unknown</database>
	</source>
	<size>
		<width>500</width>
		<height>301</height>
		<depth>3</depth>
	</size>
	<segmented>0</segmented>
	<object>
		<name>kangaroo</name>
		<pose>Unspecified</pose>
		<truncated>0</truncated>
		<difficult>0</difficult>
		<bndbox>
			<xmin>31</xmin>
			<ymin>23</ymin>
			<xmax>170</xmax>
			<ymax>286</ymax>
		</bndbox>
	</object>
	<object>
		<name>kangaroo</name>
		<pose>Unspecified</pose>
		<truncated>0</truncated>
		<difficult>0</difficult>
		<bndbox>
			<xmin>172</xmin>
			<ymin>88</ymin>
			<xmax>286</xmax>
			<ymax>250</ymax>
		</bndbox>
	</object>
	<object>
		<name>kangaroo</name>
		<pose>Unspecified</pose>
		<truncated>0</truncated>
		<difficult>0</difficult>
		<bndbox>
			<xmin>304</xmin>
			<ymin>89</ymin>
			<xmax>367</xmax>
			<ymax>246</ymax>
		</bndbox>
	</object>
	<object>
		<name>kangaroo</name>
		<pose>Unspecified</pose>
		<truncated>0</truncated>
		<difficult>0</difficult>
		<bndbox>
			<xmin>381</xmin>
			<ymin>105</ymin>
			<xmax>473</xmax>
			<ymax>255</ymax>
		</bndbox>
	</object>
</annotation>
