<annotation>
	<folder>images</folder>
	<filename>00029_640x640resized.jpg</filename>
	<path>/home/dpidave/training_resources/tf-object-detection-tutorial/Tensorflow/workspace/kangaroo/images/00029_640x640resized.jpg</path>
	<source>
		<database>Unknown</database>
	</source>
	<size>
		<width>640</width>
		<height>640</height>
		<depth>3</depth>
	</size>
	<segmented>0</segmented>
	<object>
		<name>kangaroo</name>
		<pose>Unspecified</pose>
		<truncated>0</truncated>
		<difficult>0</difficult>
		<bndbox>
			<xmin>195</xmin>
			<ymin>115</ymin>
			<xmax>481</xmax>
			<ymax>514</ymax>
		</bndbox>
	</object>
</annotation>
